gptbatcher/Choice.py
gptbatcher/GPTBatcher.py
gptbatcher/JobQueue.py
gptbatcher/Participant.py
gptbatcher/Question.py
gptbatcher/Sampler.py
gptbatcher/__init__.py
tests/__init__.py
tests/test_gptbatcher.py
gptbatcher-0.2.0.dist-info/LICENSE
gptbatcher-0.2.0.dist-info/METADATA
gptbatcher-0.2.0.dist-info/WHEEL
gptbatcher-0.2.0.dist-info/top_level.txt
gptbatcher-0.2.0.dist-info/RECORD
