Metadata-Version: 2.1
Name: gptbatcher
Version: 0.2.0
Summary: Conduct surveys using GPT
Home-page: https://github.com/CBM-Digital/GPTBatcher
Author: James O'Toole
Author-email: jamesotoole@cbmdigital.co.uk
License-File: LICENSE
Requires-Dist: openai >=1.12.0
Requires-Dist: pandas
